universal_agent_fabric/__init__.py
universal_agent_fabric/builder.py
universal_agent_fabric/cli.py
universal_agent_fabric/enricher.py
universal_agent_fabric/enrichment.py
universal_agent_fabric/schemas.py
universal_agent_fabric-0.2.1.dist-info/METADATA
universal_agent_fabric-0.2.1.dist-info/WHEEL
universal_agent_fabric-0.2.1.dist-info/entry_points.txt
universal_agent_fabric-0.2.1.dist-info/RECORD
