Metadata-Version: 2.4
Name: universal-agent-fabric
Version: 0.2.1
Summary: Composable definitions that compile to executable agent manifests for the Universal Agent Kernel
Project-URL: Homepage, https://github.com/mjdevaccount/universal_agent_fabric
Project-URL: Repository, https://github.com/mjdevaccount/universal_agent_fabric
Project-URL: Issues, https://github.com/mjdevaccount/universal_agent_fabric/issues
Author-email: Matt J <mjdevaccount@users.noreply.github.com>
License-Expression: MIT
Keywords: agents,ai,governance,llm,manifests,orchestration
Classifier: Development Status :: 3 - Alpha
Classifier: Intended Audience :: Developers
Classifier: License :: OSI Approved :: MIT License
Classifier: Programming Language :: Python :: 3
Classifier: Programming Language :: Python :: 3.10
Classifier: Programming Language :: Python :: 3.11
Classifier: Programming Language :: Python :: 3.12
Classifier: Programming Language :: Python :: 3.13
Classifier: Topic :: Software Development :: Libraries :: Python Modules
Requires-Python: >=3.10
Requires-Dist: pydantic<3,>=1.10
Requires-Dist: python-dotenv>=1.0
Requires-Dist: pyyaml>=6.0
Provides-Extra: dev
Requires-Dist: pytest>=8.0; extra == 'dev'
Requires-Dist: universal-agent-arch>=0.3.0; extra == 'dev'
